geoddb/__init__.py
geoddb/geoddb.py
geoddb/geohash.py
geoddb-0.1.1.dist-info/LICENSE
geoddb-0.1.1.dist-info/METADATA
geoddb-0.1.1.dist-info/WHEEL
geoddb-0.1.1.dist-info/top_level.txt
geoddb-0.1.1.dist-info/RECORD
