Metadata-Version: 2.1
Name: geoddb
Version: 0.1.1
Summary: Geohash and DynamoDB Utility Package
Home-page: https://github.com/khatiba/geoddb
Author: Ahmad Khatib
Author-email: ackhatib@gmail.com
License: MIT License
Platform: UNKNOWN
Classifier: Intended Audience :: Developers
Classifier: Programming Language :: Python
Classifier: Programming Language :: Python :: 3
Classifier: Programming Language :: Python :: 3.6
Classifier: Programming Language :: Python :: 3.7
Classifier: Programming Language :: Python :: 3.8
Classifier: License :: OSI Approved :: MIT License
Requires-Dist: boto3 (>=1.16)
